Workbook

Sheet Contas
A1: ID | B1: Codigo | C1: Nome | D1: Ativo
A2: 1 | B2: 1 | C2: Ativo | D2: 1
A3: 2 | B3: 1.1 | C3: Ativo Circulante | D3: 1
A4: 3 | B4: 1.1.1 | C4: Caixa | D4: 1
A5: 8 | B5: 1.1.2 | C5: Banco Sicoob | D5: 1
A6: 11 | B6: 1.1.3 | C6: Banco Sicoob Patricia | D6: 1
A7: 13 | B7: 1.1.4 | C7: Banco Sicoob RinaldoI | D7: 1
A8: 15 | B8: 1.1.5 | C8: Banco Santader | D8: 1
A9: 168 | B9: 1.1.6 | C9: Banco Santander Patricia | D9: 1
A10: 169 | B10: 1.1.7 | C10: Banco Santander Rinaldo | D10: 1
A11: 340 | B11: 1.1.8 | C11: Banco CEF | D11: 1
A12: 16 | B12: 1.2 | C12: Aplicações Financeiras | D12: 1
A13: 170 | B13: 1.2.1 | C13: Aplicação CDI CEF | D13: 1
... A74: 181 | B74: 6.5.2 | C74: Taxas Bancarias | D74: 1

Sheet Layout
A1: Data | B1: Historico | C1: Conta | D1: Valor | E1: NomeConta
A2: 16/04/2026 | B2: PIX RECEBIDO | C2: 4.1.1 | D2: 50,00 C | E2: =IFERROR(VLOOKUP(C2,Contas!B:C,2,FALSE),"") -> Receitas Operacionais
A3: 16/04/2026 | B3: PIX RECEBIDO - OUTRA IF | C3: 4.1.1 | D3: 71,00 C | E3: =IFERROR(VLOOKUP(C3,Contas!B:C,2,FALSE),"") -> Receitas Operacionais
A4: 16/04/2026 | B4: PIX RECEBIDO - OUTRA IF | C4: 4.1.1 | D4: 113,30 C | E4: =IFERROR(VLOOKUP(C4,Contas!B:C,2,FALSE),"") -> Receitas Operacionais
A5: 17/04/2026 | B5: monitoramento | C5: 6.2.4 | D5: - 220,00 D | E5: =IFERROR(VLOOKUP(C5,Contas!B:C,2,FALSE),"") -> Manutencao e Seguranca
A6: 17/04/2026 | B6: Elias congelado | C6: 5.1.1 | D6: - 285,00 D | E6: =IFERROR(VLOOKUP(C6,Contas!B:C,2,FALSE),"") -> CMV
A7: 17/04/2026 | B7: Lemon energia | C7: 6.2.1 | D7: - 776,56 D | E7: =IFERROR(VLOOKUP(C7,Contas!B:C,2,FALSE),"") -> Energia
A8: 17/04/2026 | B8: Lucimar verduras | C8: 5.1.1 | D8: - 76,00 D | E8: =IFERROR(VLOOKUP(C8,Contas!B:C,2,FALSE),"") -> CMV
A9: 17/04/2026 | B9: pix RAFAELA MENDES | C9: 4.1.1 | D9: 396,00 C | E9: =IFERROR(VLOOKUP(C9,Contas!B:C,2,FALSE),"") -> Receitas Operacionais
A10: 17/04/2026 | B10: Roberta vale | C10: 6.1.1 | D10: - 180,00 D | E10: =IFERROR(VLOOKUP(C10,Contas!B:C,2,FALSE),"") -> Salarios
A11: 17/04/2026 | B11: transf santander | C11: 1.1.5 | D11: 1.600,00 C | E11: =IFERROR(VLOOKUP(C11,Contas!B:C,2,FALSE),"") -> Banco Santader
A12: 20/04/2026 | B12: agua chacar | C12: 6.1.2 | D12: - 459,22 D | E12: =IFERROR(VLOOKUP(C12,Contas!B:C,2,FALSE),"") -> Pro-labore
A13: 20/04/2026 | B13: Brejeiro | C13: 5.1.1 | D13: - 1.143,75 D | E13: =IFERROR(VLOOKUP(C13,Contas!B:C,2,FALSE),"") -> CMV
... A57: 24/04/2026 | B57: PIX RECEBIDO - OUTRA IF | C57: 4.1.1 | D57: 96,00 C | E57: =IFERROR(VLOOKUP(C57,Contas!B:C,2,FALSE),"") -> Receitas Operacionais
E58: =IFERROR(VLOOKUP(C58,Contas!B:C,2,FALSE),"")
E59: =IFERROR(VLOOKUP(C59,Contas!B:C,2,FALSE),"")
E60: =IFERROR(VLOOKUP(C60,Contas!B:C,2,FALSE),"")
E61: =IFERROR(VLOOKUP(C61,Contas!B:C,2,FALSE),"")
E62: =IFERROR(VLOOKUP(C62,Contas!B:C,2,FALSE),"")
E63: =IFERROR(VLOOKUP(C63,Contas!B:C,2,FALSE),"")
E64: =IFERROR(VLOOKUP(C64,Contas!B:C,2,FALSE),"")
E65: =IFERROR(VLOOKUP(C65,Contas!B:C,2,FALSE),"")
E66: =IFERROR(VLOOKUP(C66,Contas!B:C,2,FALSE),"")
E67: =IFERROR(VLOOKUP(C67,Contas!B:C,2,FALSE),"")
E68: =IFERROR(VLOOKUP(C68,Contas!B:C,2,FALSE),"")
E69: =IFERROR(VLOOKUP(C69,Contas!B:C,2,FALSE),"")
... E200: =IFERROR(VLOOKUP(C200,Contas!B:C,2,FALSE),"")
